highteacli/__init__.py
highteacli/apiactions.py
highteacli/app.py
highteacli-0.5.dist-info/entry_points.txt
highteacli-0.5.dist-info/LICENSE
highteacli-0.5.dist-info/WHEEL
highteacli-0.5.dist-info/METADATA
highteacli-0.5.dist-info/RECORD
