Metadata-Version: 2.1
Name: highteacli
Version: 0.5
Summary: A command line interface for the high energy theory database.
Home-page: https://github.com/Zaharid/highteacli
License: UNKNOWN
Author: Zahari Kassabov
Author-email: zaharid@protonmail.com
Requires-Python: >3.6
Classifier: License :: OSI Approved :: MIT License
Requires-Dist: requests
